tytodb_client/__init__.py
tytodb_pyclient-0.1.6.dist-info/licenses/LICENSE
tytodb_pyclient-0.1.6.dist-info/METADATA
tytodb_pyclient-0.1.6.dist-info/WHEEL
tytodb_pyclient-0.1.6.dist-info/top_level.txt
tytodb_pyclient-0.1.6.dist-info/RECORD
